{
    "snapshots": [
        {
            "data": {
                "ph1_lv2": {
                    "parameters": {},
                    "ports": {
                        "speed": 0.10000000149011612
                    },
                    "preset": "",
                    "bypassed": true
                },
                "wah1_lv2": {
                    "parameters": {},
                    "ports": {
                        "sensitivity": 1.0
                    },
                    "preset": "",
                    "bypassed": false
                },
                "xfade": {
                    "parameters": {},
                    "ports": {
                        "shape": 0.0,
                        "xfade": 1.0,
                        "mode": 0.0
                    },
                    "preset": "",
                    "bypassed": true
                },
                "cr1_lv2": {
                    "parameters": {},
                    "ports": {
                        "speed": 3.75,
                        "depth": 5.0
                    },
                    "preset": "",
                    "bypassed": true
                },
                "dt1_lv2": {
                    "parameters": {},
                    "ports": {
                        "level": 10.0,
                        "drive": 2.0
                    },
                    "preset": "",
                    "bypassed": true
                },
                "Gain": {
                    "parameters": {},
                    "ports": {
                        "Gain": -6.0
                    },
                    "preset": "",
                    "bypassed": false
                },
                "Gain2x2": {
                    "parameters": {},
                    "ports": {
                        "Gain": -2.0
                    },
                    "preset": "",
                    "bypassed": false
                },
                "Gain2x2_1": {
                    "parameters": {},
                    "ports": {
                        "Gain": 0.0
                    },
                    "preset": "",
                    "bypassed": false
                }
            },
            "name": "Wah"
        },
        {
            "data": {
                "ph1_lv2": {
                    "parameters": {},
                    "ports": {
                        "speed": 0.10000000149011612
                    },
                    "preset": "",
                    "bypassed": false
                },
                "wah1_lv2": {
                    "parameters": {},
                    "ports": {
                        "sensitivity": 1.0
                    },
                    "preset": "",
                    "bypassed": false
                },
                "xfade": {
                    "parameters": {},
                    "ports": {
                        "shape": 0.0,
                        "xfade": 1.0,
                        "mode": 0.0
                    },
                    "preset": "",
                    "bypassed": true
                },
                "cr1_lv2": {
                    "parameters": {},
                    "ports": {
                        "speed": 3.75,
                        "depth": 5.0
                    },
                    "preset": "",
                    "bypassed": true
                },
                "dt1_lv2": {
                    "parameters": {},
                    "ports": {
                        "level": 10.0,
                        "drive": 2.0
                    },
                    "preset": "",
                    "bypassed": true
                },
                "Gain": {
                    "parameters": {},
                    "ports": {
                        "Gain": -6.0
                    },
                    "preset": "",
                    "bypassed": false
                },
                "Gain2x2": {
                    "parameters": {},
                    "ports": {
                        "Gain": -2.0
                    },
                    "preset": "",
                    "bypassed": false
                },
                "Gain2x2_1": {
                    "parameters": {},
                    "ports": {
                        "Gain": 0.0
                    },
                    "preset": "",
                    "bypassed": false
                }
            },
            "name": "Phase Wah"
        },
        {
            "data": {
                "ph1_lv2": {
                    "parameters": {},
                    "ports": {
                        "speed": 0.10000000149011612
                    },
                    "preset": "",
                    "bypassed": false
                },
                "wah1_lv2": {
                    "parameters": {},
                    "ports": {
                        "sensitivity": 1.0
                    },
                    "preset": "",
                    "bypassed": true
                },
                "xfade": {
                    "parameters": {},
                    "ports": {
                        "shape": 0.0,
                        "xfade": 1.0,
                        "mode": 0.0
                    },
                    "preset": "",
                    "bypassed": true
                },
                "cr1_lv2": {
                    "parameters": {},
                    "ports": {
                        "speed": 3.75,
                        "depth": 5.0
                    },
                    "preset": "",
                    "bypassed": true
                },
                "dt1_lv2": {
                    "parameters": {},
                    "ports": {
                        "level": 10.0,
                        "drive": 2.0
                    },
                    "preset": "",
                    "bypassed": false
                },
                "Gain": {
                    "parameters": {},
                    "ports": {
                        "Gain": -6.0
                    },
                    "preset": "",
                    "bypassed": false
                },
                "Gain2x2": {
                    "parameters": {},
                    "ports": {
                        "Gain": -2.0
                    },
                    "preset": "",
                    "bypassed": false
                },
                "Gain2x2_1": {
                    "parameters": {},
                    "ports": {
                        "Gain": 0.0
                    },
                    "preset": "",
                    "bypassed": false
                }
            },
            "name": "Driven Phaser"
        },
        {
            "data": {
                "ph1_lv2": {
                    "parameters": {},
                    "ports": {
                        "speed": 0.10000000149011612
                    },
                    "preset": "",
                    "bypassed": true
                },
                "wah1_lv2": {
                    "parameters": {},
                    "ports": {
                        "sensitivity": 1.0
                    },
                    "preset": "",
                    "bypassed": true
                },
                "xfade": {
                    "parameters": {},
                    "ports": {
                        "shape": 0.0,
                        "xfade": 1.0,
                        "mode": 0.0
                    },
                    "preset": "",
                    "bypassed": true
                },
                "cr1_lv2": {
                    "parameters": {},
                    "ports": {
                        "speed": 3.75,
                        "depth": 5.0
                    },
                    "preset": "",
                    "bypassed": false
                },
                "dt1_lv2": {
                    "parameters": {},
                    "ports": {
                        "level": 10.0,
                        "drive": 2.0
                    },
                    "preset": "",
                    "bypassed": true
                },
                "Gain": {
                    "parameters": {},
                    "ports": {
                        "Gain": -6.0
                    },
                    "preset": "",
                    "bypassed": false
                },
                "Gain2x2": {
                    "parameters": {},
                    "ports": {
                        "Gain": -2.0
                    },
                    "preset": "",
                    "bypassed": false
                },
                "Gain2x2_1": {
                    "parameters": {},
                    "ports": {
                        "Gain": 0.0
                    },
                    "preset": "",
                    "bypassed": false
                }
            },
            "name": "Chorus"
        },
        {
            "data": {
                "ph1_lv2": {
                    "parameters": {},
                    "ports": {
                        "speed": 0.10000000149011612
                    },
                    "preset": "",
                    "bypassed": true
                },
                "wah1_lv2": {
                    "parameters": {},
                    "ports": {
                        "sensitivity": 1.0
                    },
                    "preset": "",
                    "bypassed": true
                },
                "xfade": {
                    "parameters": {},
                    "ports": {
                        "shape": 0.0,
                        "xfade": 1.0,
                        "mode": 0.0
                    },
                    "preset": "",
                    "bypassed": true
                },
                "cr1_lv2": {
                    "parameters": {},
                    "ports": {
                        "speed": 3.75,
                        "depth": 5.0
                    },
                    "preset": "",
                    "bypassed": false
                },
                "dt1_lv2": {
                    "parameters": {},
                    "ports": {
                        "level": 10.0,
                        "drive": 2.0
                    },
                    "preset": "",
                    "bypassed": false
                },
                "Gain": {
                    "parameters": {},
                    "ports": {
                        "Gain": -6.0
                    },
                    "preset": "",
                    "bypassed": false
                },
                "Gain2x2": {
                    "parameters": {},
                    "ports": {
                        "Gain": -2.0
                    },
                    "preset": "",
                    "bypassed": false
                },
                "Gain2x2_1": {
                    "parameters": {},
                    "ports": {
                        "Gain": 0.0
                    },
                    "preset": "",
                    "bypassed": false
                }
            },
            "name": "Driven Chorus"
        }
    ],
    "current": 0
}