{
    "/hmi/group1": [],
    "/hmi/footswitch1": [
        {
            "port": ":bypass",
            "group": null,
            "steps": 33,
            "tempo": null,
            "maximum": 1.0,
            "label": "Roomy",
            "page": null,
            "instance": "/graph/roomy",
            "minimum": 0.0,
            "dividers": null
        }
    ],
    "/hmi/footswitch2": [
        {
            "port": ":bypass",
            "group": null,
            "steps": 33,
            "tempo": null,
            "maximum": 1.0,
            "label": "Harmless",
            "page": null,
            "instance": "/graph/harmless",
            "minimum": 0.0,
            "dividers": null
        }
    ],
    "/hmi/knob2": [
        {
            "port": "rate",
            "group": null,
            "steps": 33,
            "tempo": null,
            "maximum": 20.0,
            "label": "rate",
            "page": null,
            "instance": "/graph/harmless",
            "minimum": 0.10000000149011612,
            "dividers": null
        },
        {
            "port": "Gain",
            "group": null,
            "steps": 33,
            "tempo": null,
            "maximum": 20.0,
            "label": "Master Volume",
            "page": null,
            "instance": "/graph/Gain2x2",
            "minimum": -20.0,
            "dividers": null
        }
    ],
    "/hmi/knob1": [
        {
            "port": "hardness",
            "group": null,
            "steps": 33,
            "tempo": null,
            "maximum": 50.0,
            "label": "Hardness",
            "page": null,
            "instance": "/graph/EPiano",
            "minimum": -50.0,
            "dividers": null
        },
        {
            "port": "time",
            "group": null,
            "steps": 33,
            "tempo": null,
            "maximum": 1.0,
            "label": "Decay",
            "page": null,
            "instance": "/graph/roomy",
            "minimum": 0.0,
            "dividers": null
        }
    ],
    "/bpm": []
}