[{"navigateChannel": 16, "title": "Clean Guitar Simulator", "navigateFootswitches": true, "pedalboards": [{"bundle": "/root/.pedalboards/Basic_Clean_Guitar.pedalboard", "title": "Basic Clean Guitar"}, {"bundle": "/root/.pedalboards/Basic_Clean_Guitar_Loop.pedalboard", "title": "Basic Clean Guitar Loop"}, {"bundle": "/root/.pedalboards/Chorus_Flange_Cl.pedalboard", "title": "Chorus Flange Clean Guitar"}, {"bundle": "/root/.pedalboards/DubDelay_Clean_Guitar.pedalboard", "title": "DubDelay Clean Guitar"}, {"bundle": "/root/.pedalboards/Phaser_Clean_Gui.pedalboard", "title": "Phaser Clean Guitar"}, {"bundle": "/root/.pedalboards/Tremolo_Clean_Gu.pedalboard", "title": "Tremolo Clean Guitar"}, {"bundle": "/root/.pedalboards/Wah_Clean_Guitar-7582.pedalboard", "title": "Wah Clean Guitar"}]}, {"navigateChannel": 16, "title": "CAPS Guitar Amp Simulation", "navigateFootswitches": true, "pedalboards": [{"bundle": "/root/.pedalboards/CAPS_Basic_Guita-18005.pedalboard", "title": "CAPS Basic Guitar"}, {"bundle": "/root/.pedalboards/CAPS_Basic_Guita.pedalboard", "title": "CAPS Basic Guitar II"}, {"bundle": "/root/.pedalboards/CAPS_OverDrive_G.pedalboard", "title": "CAPS OverDrive Guitar"}, {"bundle": "/root/.pedalboards/Big_Muff_CAPS_Gu.pedalboard", "title": "Big Muff CAPS Guitar"}, {"bundle": "/root/.pedalboards/CAPS_TScream_Gui.pedalboard", "title": "CAPS TScream Guitar"}, {"bundle": "/root/.pedalboards/Wah_CAPS_Guitar.pedalboard", "title": "Wah CAPS Guitar"}, {"bundle": "/root/.pedalboards/CAPS_Multi_Effec.pedalboard", "title": "CAPS Multi Effects"}]}, {"navigateChannel": 16, "title": "Distortions WO amp sim", "navigateFootswitches": false, "pedalboards": [{"bundle": "/root/.pedalboards/Big_Muff.pedalboard", "title": "Big Muff"}, {"bundle": "/root/.pedalboards/DS_1.pedalboard", "title": "DS-1"}, {"bundle": "/root/.pedalboards/Fuzz_Face_FM.pedalboard", "title": "Fuzz Face FM"}, {"bundle": "/root/.pedalboards/Screaming_Bird.pedalboard", "title": "Screaming Bird"}, {"bundle": "/root/.pedalboards/Tilt_Tone.pedalboard", "title": "Tilt Tone"}, {"bundle": "/root/.pedalboards/Tube_Screamer.pedalboard", "title": "Tube Screamer"}]}, {"navigateChannel": 16, "title": "Modulator WO amp sim", "navigateFootswitches": false, "pedalboards": [{"bundle": "/root/.pedalboards/Auto_Tune.pedalboard", "title": "Auto Tune"}, {"bundle": "/root/.pedalboards/Chorus_Flanger.pedalboard", "title": "Chorus-Flanger"}, {"bundle": "/root/.pedalboards/Detuner.pedalboard", "title": "Detuner"}, {"bundle": "/root/.pedalboards/Fractal_Doubler.pedalboard", "title": "Fractal Doubler"}, {"bundle": "/root/.pedalboards/Invada_Phaser.pedalboard", "title": "Invada Phaser"}, {"bundle": "/root/.pedalboards/Invada_Phaser.pedalboard", "title": "Invada Phaser"}, {"bundle": "/root/.pedalboards/Hall_Reverb.pedalboard", "title": "Hall Reverb"}, {"bundle": "/root/.pedalboards/Vibrato.pedalboard", "title": "Vibrato"}, {"bundle": "/root/.pedalboards/Reflector.pedalboard", "title": "Reflector"}, {"bundle": "/root/.pedalboards/Tremolo.pedalboard", "title": "Tremolo"}, {"bundle": "/root/.pedalboards/Stereo_Echo.pedalboard", "title": "Stereo Echo"}, {"bundle": "/root/.pedalboards/Sound_Scape.pedalboard", "title": "Sound Scape"}, {"bundle": "/root/.pedalboards/Simple_Equalizer.pedalboard", "title": "Simple Equalizer"}, {"bundle": "/root/.pedalboards/Shimmer_Reverb.pedalboard", "title": "Shimmer Reverb"}, {"bundle": "/root/.pedalboards/Ring_Modulator.pedalboard", "title": "Ring Modulator"}, {"bundle": "/root/.pedalboards/Ping_Pong_Pan.pedalboard", "title": "Ping Pong Pan"}]}]