[{"navigateChannel": 16, "pedalboards": [{"bundle": "/root/.pedalboards/default.pedalboard", "title": "Default"}], "navigateFootswitches": false, "title": "Instrument Independent"}, {"navigateChannel": 16, "pedalboards": [{"bundle": "/root/.pedalboards/default.pedalboard", "title": "Default"}], "navigateFootswitches": false, "title": "Guitar"}, {"navigateChannel": 16, "pedalboards": [{"bundle": "/root/.pedalboards/M_ST_Clean.pedalboard", "title": "M/ST Clean"}, {"bundle": "/root/.pedalboards/M_ST_Rich_Clean.pedalboard", "title": "M/ST Rich Clean"}, {"bundle": "/root/.pedalboards/M_ST_Silly_Funky.pedalboard", "title": "M/ST Silly Funky Clean"}, {"bundle": "/root/.pedalboards/M_ST_Vibro.pedalboard", "title": "M/ST Vibro"}, {"bundle": "/root/.pedalboards/M_ST_Breakup.pedalboard", "title": "M/ST Breakup"}, {"bundle": "/root/.pedalboards/M_ST_Moody_Texas.pedalboard", "title": "M/ST Moody Texas Breakup"}], "navigateFootswitches": false, "title": "Guitar Ampsim"}, {"navigateChannel": 16, "pedalboards": [{"bundle": "/root/.pedalboards/M_ST_Autotune.pedalboard", "title": "M/ST Autotune"}, {"bundle": "/root/.pedalboards/M_DIN_ST_Vocoder.pedalboard", "title": "M+DIN/ST Vocoder"}], "navigateFootswitches": false, "title": "Vocals"}, {"navigateChannel": 16, "pedalboards": [{"bundle": "/root/.pedalboards/default.pedalboard", "title": "Default"}], "navigateFootswitches": false, "title": "Synth or Keys"}]