{
    "/hmi/potentiometer3": [
        {
            "group": null,
            "coloured": false,
            "tempo": false,
            "subpage": null,
            "label": "Decay",
            "maximum": 7000.0,
            "instance": "/graph/DX10",
            "minimum": 46.5,
            "momentary": 0,
            "dividers": null,
            "port": "decay",
            "steps": 33,
            "page": 0
        }
    ],
    "/hmi/potentiometer2": [
        {
            "group": null,
            "coloured": false,
            "tempo": false,
            "subpage": null,
            "label": "Waveform",
            "maximum": 100.0,
            "instance": "/graph/DX10",
            "minimum": 0.0,
            "momentary": 0,
            "dividers": {
                "options": [],
                "value": null
            },
            "port": "waveform",
            "steps": 33,
            "page": 0
        }
    ],
    "/hmi/potentiometer1": [
        {
            "group": null,
            "coloured": false,
            "tempo": false,
            "subpage": null,
            "label": "Attack",
            "maximum": 4000.0,
            "instance": "/graph/DX10",
            "minimum": 2.5,
            "momentary": 0,
            "dividers": null,
            "port": "attack",
            "steps": 33,
            "page": 0
        }
    ],
    "/hmi/potentiometer7": [
        {
            "group": null,
            "coloured": false,
            "tempo": false,
            "subpage": null,
            "label": "Mod Dec",
            "maximum": 7000.0,
            "instance": "/graph/DX10",
            "minimum": 17.0,
            "momentary": 0,
            "dividers": null,
            "port": "mod_dec",
            "steps": 33,
            "page": 0
        }
    ],
    "/hmi/potentiometer6": [
        {
            "group": null,
            "coloured": false,
            "tempo": false,
            "subpage": null,
            "label": "Mod Sus",
            "maximum": 100.0,
            "instance": "/graph/DX10",
            "minimum": 0.0,
            "momentary": 0,
            "dividers": {
                "options": [],
                "value": null
            },
            "port": "mod_sus",
            "steps": 33,
            "page": 0
        }
    ],
    "/hmi/potentiometer5": [
        {
            "group": null,
            "coloured": false,
            "tempo": false,
            "subpage": null,
            "label": "Mod Init",
            "maximum": 100.0,
            "instance": "/graph/DX10",
            "minimum": 0.0,
            "momentary": 0,
            "dividers": {
                "options": [],
                "value": null
            },
            "port": "mod_init",
            "steps": 33,
            "page": 0
        }
    ],
    "/hmi/potentiometer4": [
        {
            "group": null,
            "coloured": false,
            "tempo": false,
            "subpage": null,
            "label": "Release",
            "maximum": 7000.0,
            "instance": "/graph/DX10",
            "minimum": 46.5,
            "momentary": 0,
            "dividers": null,
            "port": "release",
            "steps": 33,
            "page": 0
        }
    ],
    "/cv/graph/cv_exp_pedal": [],
    "/cv/graph/cv_capture_1": [],
    "/hmi/potentiometer8": [
        {
            "group": null,
            "coloured": false,
            "tempo": false,
            "subpage": null,
            "label": "Mod Rel",
            "maximum": 7000.0,
            "instance": "/graph/DX10",
            "minimum": 46.5,
            "momentary": 0,
            "dividers": null,
            "port": "mod_rel",
            "steps": 33,
            "page": 0
        }
    ],
    "/cv/graph/cv_capture_2": [],
    "/bpm": [],
    "/hmi/group2": [],
    "/hmi/group3": [],
    "/hmi/group1": [],
    "/hmi/footswitch4": [
        {
            "group": null,
            "coloured": false,
            "tempo": false,
            "subpage": null,
            "label": "Shiro DOWN",
            "maximum": 1.0,
            "instance": "/graph/shiroverb_1",
            "minimum": 0.0,
            "momentary": 0,
            "dividers": {
                "options": []
            },
            "port": ":bypass",
            "steps": 33,
            "page": 0
        }
    ],
    "/hmi/knob1": [
        {
            "group": null,
            "coloured": false,
            "tempo": false,
            "subpage": null,
            "label": "Coarse",
            "maximum": 40.0,
            "instance": "/graph/DX10",
            "minimum": 0.0,
            "momentary": 0,
            "dividers": null,
            "port": "coarse",
            "steps": 40,
            "page": 0
        }
    ],
    "/hmi/knob2": [
        {
            "group": null,
            "coloured": false,
            "tempo": false,
            "subpage": null,
            "label": "Fine",
            "maximum": 0.75,
            "instance": "/graph/DX10",
            "minimum": 0.0010000000474974513,
            "momentary": 0,
            "dividers": null,
            "port": "fine",
            "steps": 33,
            "page": 0
        }
    ],
    "/hmi/footswitch1": [
        {
            "group": null,
            "coloured": false,
            "tempo": false,
            "subpage": null,
            "label": "Glitch/Stutter",
            "maximum": 1.0,
            "instance": "/graph/xfade",
            "minimum": 0.0,
            "momentary": 0,
            "dividers": {
                "options": []
            },
            "port": ":bypass",
            "steps": 33,
            "page": 0
        }
    ],
    "/hmi/footswitch2": [
        {
            "group": null,
            "coloured": false,
            "tempo": false,
            "subpage": null,
            "label": "Chorus/Flanger",
            "maximum": 1.0,
            "instance": "/graph/chorusflanger",
            "minimum": 0.0,
            "momentary": 0,
            "dividers": {
                "options": []
            },
            "port": ":bypass",
            "steps": 33,
            "page": 0
        }
    ],
    "/hmi/footswitch3": [
        {
            "group": null,
            "coloured": false,
            "tempo": false,
            "subpage": null,
            "label": "Shiro UP",
            "maximum": 1.0,
            "instance": "/graph/shiroverb",
            "minimum": 0.0,
            "momentary": 0,
            "dividers": {
                "options": []
            },
            "port": ":bypass",
            "steps": 33,
            "page": 0
        }
    ]
}