{
    "/bpm": [],
    "/hmi/group1": [],
    "/hmi/footswitch2": [
        {
            "coloured": false,
            "instance": "/graph/xfade_1",
            "steps": 201,
            "subpage": 0,
            "page": 0,
            "momentary": 0,
            "label": "-Octave",
            "tempo": false,
            "maximum": 1.0,
            "dividers": null,
            "group": null,
            "port": ":bypass",
            "minimum": 0.0
        }
    ],
    "/hmi/knob3": [
        {
            "coloured": false,
            "instance": "/graph/mono",
            "steps": 201,
            "subpage": 0,
            "page": 0,
            "momentary": 0,
            "label": "Ratio",
            "tempo": false,
            "maximum": 20.0,
            "dividers": null,
            "group": null,
            "port": "ratio",
            "minimum": 1.0
        },
        {
            "coloured": false,
            "instance": "/graph/cabsim_bass",
            "steps": 3,
            "subpage": 2,
            "page": 0,
            "momentary": 0,
            "label": "Mic Position",
            "tempo": false,
            "maximum": 3.0,
            "dividers": null,
            "group": null,
            "port": "MicPos",
            "minimum": 0.0
        },
        {
            "coloured": false,
            "instance": "/graph/_ampegsvt_",
            "steps": 201,
            "subpage": 1,
            "page": 0,
            "momentary": 0,
            "label": "TREBLE",
            "tempo": false,
            "maximum": 1.0,
            "dividers": null,
            "group": null,
            "port": "TREBLE",
            "minimum": 0.0
        }
    ],
    "/hmi/knob2": [
        {
            "coloured": false,
            "instance": "/graph/mono",
            "steps": 201,
            "subpage": 0,
            "page": 0,
            "momentary": 0,
            "label": "Threshold",
            "tempo": false,
            "maximum": 0.0,
            "dividers": null,
            "group": null,
            "port": "threshold",
            "minimum": -36.0
        },
        {
            "coloured": false,
            "instance": "/graph/cabsim_bass",
            "steps": 5,
            "subpage": 2,
            "page": 0,
            "momentary": 0,
            "label": "Cabinet",
            "tempo": false,
            "maximum": 5.0,
            "dividers": null,
            "group": null,
            "port": "Model",
            "minimum": 0.0
        },
        {
            "coloured": false,
            "instance": "/graph/_ampegsvt_",
            "steps": 201,
            "subpage": 1,
            "page": 0,
            "momentary": 0,
            "label": "MIDDLE",
            "tempo": false,
            "maximum": 1.0,
            "dividers": null,
            "group": null,
            "port": "MIDDLE",
            "minimum": 0.0
        }
    ],
    "/hmi/knob1": [
        {
            "coloured": false,
            "instance": "/graph/xfade",
            "steps": 201,
            "subpage": 0,
            "page": 0,
            "momentary": 0,
            "label": "Dry/Comp",
            "tempo": false,
            "maximum": 1.0,
            "dividers": null,
            "group": null,
            "port": "xfade",
            "minimum": -1.0
        },
        {
            "coloured": false,
            "instance": "/graph/_ampegsvt_",
            "steps": 201,
            "subpage": 1,
            "page": 0,
            "momentary": 0,
            "label": "BASS",
            "tempo": false,
            "maximum": 1.0,
            "dividers": null,
            "group": null,
            "port": "BASS",
            "minimum": 0.0
        },
        {
            "coloured": false,
            "instance": "/graph/cabsim_bass",
            "steps": 201,
            "subpage": 2,
            "page": 0,
            "momentary": 0,
            "label": "Attenuation",
            "tempo": false,
            "maximum": 0.0,
            "dividers": null,
            "group": null,
            "port": "Attenuation",
            "minimum": -90.0
        }
    ],
    "/hmi/footswitch1": [
        {
            "coloured": false,
            "instance": "/graph/xfade",
            "steps": 201,
            "subpage": 0,
            "page": 0,
            "momentary": 0,
            "label": "Compressor",
            "tempo": false,
            "maximum": 1.0,
            "dividers": null,
            "group": null,
            "port": ":bypass",
            "minimum": 0.0
        }
    ]
}