{"/hmi/knob1": [{"steps": 14, "port": "function", "instance": "/graph/dynamics", "minimum": 0.0, "label": "Function", "maximum": 14.0}, {"steps": 33, "port": "attack", "instance": "/graph/dynamics", "minimum": 4.0, "label": "Attack", "maximum": 500.0}, {"steps": 33, "port": "release", "instance": "/graph/dynamics", "minimum": 4.0, "label": "Release", "maximum": 1000.0}], "/hmi/knob2": [{"steps": 33, "port": "makeup", "instance": "/graph/dynamics", "minimum": -20.0, "label": "Makeup Gain", "maximum": 20.0}, {"steps": 33, "port": "offset", "instance": "/graph/dynamics", "minimum": -20.0, "label": "Offset Gain", "maximum": 20.0}], "/hmi/footswitch1": [{"steps": 33, "port": ":bypass", "instance": "/graph/dynamics", "minimum": 0.0, "label": "Dynamics", "maximum": 1.0}], "/hmi/footswitch2": [{"steps": 33, "port": ":bypass", "instance": "/graph/HardwareBypass", "minimum": 0.0, "label": "T.Bypass", "maximum": 1.0}]}