{
    "/hmi/group1": [],
    "/hmi/knob2": [
        {
            "momentary": 0,
            "port": "Level",
            "group": null,
            "instance": "/graph/BigMuffPi",
            "page": 0,
            "dividers": null,
            "coloured": false,
            "tempo": false,
            "subpage": 0,
            "maximum": 1.0,
            "steps": 201,
            "label": "Level",
            "minimum": 0.0
        },
        {
            "momentary": 0,
            "port": "TONE",
            "group": null,
            "instance": "/graph/_bajatubedriver_",
            "page": 0,
            "dividers": null,
            "coloured": false,
            "tempo": false,
            "subpage": 1,
            "maximum": 1.0,
            "steps": 201,
            "label": "TONE",
            "minimum": 0.0
        },
        {
            "momentary": 0,
            "port": "decay",
            "group": null,
            "instance": "/graph/shiroverb",
            "page": 1,
            "dividers": null,
            "coloured": false,
            "tempo": false,
            "subpage": 0,
            "maximum": 50.0,
            "steps": 201,
            "label": "decay",
            "minimum": 1.0
        },
        {
            "momentary": 0,
            "port": "depth",
            "group": null,
            "instance": "/graph/PhaserII",
            "page": 1,
            "dividers": null,
            "coloured": false,
            "tempo": false,
            "subpage": 1,
            "maximum": 1.0,
            "steps": 201,
            "label": "Depth",
            "minimum": 0.0
        }
    ],
    "/hmi/knob3": [
        {
            "momentary": 0,
            "port": "Sustain",
            "group": null,
            "instance": "/graph/BigMuffPi",
            "page": 0,
            "dividers": null,
            "coloured": false,
            "tempo": false,
            "subpage": 0,
            "maximum": 1.0,
            "steps": 201,
            "label": "Sustain",
            "minimum": 0.0
        },
        {
            "momentary": 0,
            "port": "VOLUME",
            "group": null,
            "instance": "/graph/_bajatubedriver_",
            "page": 0,
            "dividers": null,
            "coloured": false,
            "tempo": false,
            "subpage": 1,
            "maximum": 1.0,
            "steps": 201,
            "label": "VOLUME",
            "minimum": 0.0
        },
        {
            "momentary": 0,
            "port": "tone",
            "group": null,
            "instance": "/graph/shiroverb",
            "page": 1,
            "dividers": null,
            "coloured": false,
            "tempo": false,
            "subpage": 0,
            "maximum": 6000.0,
            "steps": 201,
            "label": "tone",
            "minimum": 500.0
        },
        {
            "momentary": 0,
            "port": "resonance",
            "group": null,
            "instance": "/graph/PhaserII",
            "page": 1,
            "dividers": null,
            "coloured": false,
            "tempo": false,
            "subpage": 1,
            "maximum": 1.0,
            "steps": 201,
            "label": "Resonance",
            "minimum": 0.0
        }
    ],
    "/hmi/knob1": [
        {
            "momentary": 0,
            "port": "Tone",
            "group": null,
            "instance": "/graph/BigMuffPi",
            "page": 0,
            "dividers": null,
            "coloured": false,
            "tempo": false,
            "subpage": 0,
            "maximum": 1.0,
            "steps": 201,
            "label": "Tone",
            "minimum": 0.0
        },
        {
            "momentary": 0,
            "port": "DRIVE",
            "group": null,
            "instance": "/graph/_bajatubedriver_",
            "page": 0,
            "dividers": null,
            "coloured": false,
            "tempo": false,
            "subpage": 1,
            "maximum": 1.0,
            "steps": 201,
            "label": "DRIVE",
            "minimum": 0.0
        },
        {
            "momentary": 0,
            "port": "mix",
            "group": null,
            "instance": "/graph/shiroverb",
            "page": 1,
            "dividers": null,
            "coloured": false,
            "tempo": false,
            "subpage": 0,
            "maximum": 100.0,
            "steps": 201,
            "label": "mix",
            "minimum": 0.0
        },
        {
            "momentary": 0,
            "port": "rate",
            "group": null,
            "instance": "/graph/PhaserII",
            "page": 1,
            "dividers": null,
            "coloured": false,
            "tempo": false,
            "subpage": 1,
            "maximum": 1.0,
            "steps": 201,
            "label": "Rate",
            "minimum": 0.0
        }
    ],
    "/hmi/footswitch2": [
        {
            "momentary": 0,
            "port": ":bypass",
            "group": null,
            "instance": "/graph/_bajatubedriver_",
            "page": 0,
            "dividers": null,
            "coloured": false,
            "tempo": false,
            "subpage": 0,
            "maximum": 1.0,
            "steps": 33,
            "label": "TubeDRV",
            "minimum": 0.0
        },
        {
            "momentary": 0,
            "port": ":bypass",
            "group": null,
            "instance": "/graph/PhaserII",
            "page": 1,
            "dividers": null,
            "coloured": false,
            "tempo": false,
            "subpage": 0,
            "maximum": 1.0,
            "steps": 33,
            "label": "PhaserII",
            "minimum": 0.0
        }
    ],
    "/bpm": [],
    "/hmi/footswitch1": [
        {
            "momentary": 0,
            "port": ":bypass",
            "group": null,
            "instance": "/graph/BigMuffPi",
            "page": 0,
            "dividers": null,
            "coloured": false,
            "tempo": false,
            "subpage": 0,
            "maximum": 1.0,
            "steps": 33,
            "label": "Big Muff",
            "minimum": 0.0
        },
        {
            "momentary": 0,
            "port": ":bypass",
            "group": null,
            "instance": "/graph/shiroverb",
            "page": 1,
            "dividers": null,
            "coloured": false,
            "tempo": false,
            "subpage": 0,
            "maximum": 1.0,
            "steps": 33,
            "label": "Verb",
            "minimum": 0.0
        }
    ]
}